YoukuAppQuanliangZhichiAnheiMoshiShejiYuJishuWanzhengZongjieFix1/README.md
YoukuAppQuanliangZhichiAnheiMoshiShejiYuJishuWanzhengZongjieFix1/__init__.py
YoukuAppQuanliangZhichiAnheiMoshiShejiYuJishuWanzhengZongjieFix1/__main__.py
YoukuAppQuanliangZhichiAnheiMoshiShejiYuJishuWanzhengZongjieFix1/file.pdf
YoukuAppQuanliangZhichiAnheiMoshiShejiYuJishuWanzhengZongjieFix1/index.html
youku_app_quanliang_zhichi_anhei_moshi_sheji_yu_jishu_wanzheng_zongjie_fix1-2025.3.25.0.dist-info/METADATA
youku_app_quanliang_zhichi_anhei_moshi_sheji_yu_jishu_wanzheng_zongjie_fix1-2025.3.25.0.dist-info/WHEEL
youku_app_quanliang_zhichi_anhei_moshi_sheji_yu_jishu_wanzheng_zongjie_fix1-2025.3.25.0.dist-info/entry_points.txt
youku_app_quanliang_zhichi_anhei_moshi_sheji_yu_jishu_wanzheng_zongjie_fix1-2025.3.25.0.dist-info/top_level.txt
youku_app_quanliang_zhichi_anhei_moshi_sheji_yu_jishu_wanzheng_zongjie_fix1-2025.3.25.0.dist-info/RECORD
