Metadata-Version: 2.1
Name: youku-app-quanliang-zhichi-anhei-moshi-sheji-yu-jishu-wanzheng-zongjie-fix1
Version: 2025.3.25.0
Summary: 优酷 APP 全量支持“暗黑模式” ——设计与技术完整总结
Home-page: https://github.com/apachecn/youku-app-quanliang-zhichi-anhei-moshi-sheji-yu-jishu-wanzheng-zongjie-fix1
Author: ApacheCN
Author-email: apachecn@163.com
Classifier: Development Status :: 4 - Beta
Classifier: Environment :: Console
Classifier: Intended Audience :: Developers
Classifier: Intended Audience :: End Users/Desktop
Classifier: License :: Other/Proprietary License
Classifier: Natural Language :: Chinese (Simplified)
Classifier: Natural Language :: English
Classifier: Operating System :: OS Independent
Classifier: Programming Language :: Python :: 3
Classifier: Programming Language :: Python :: 3 :: Only
Classifier: Programming Language :: Python :: 3.6
Classifier: Programming Language :: Python :: 3.7
Classifier: Topic :: Text Processing :: Markup :: Markdown
Classifier: Topic :: Text Processing :: Markup :: HTML
Classifier: Topic :: Internet :: WWW/HTTP
Classifier: Topic :: Software Development :: Documentation
Classifier: Topic :: Documentation
Requires-Python: >=3.6
